pydantic_commands/__init__.py
pydantic_commands/base.py
pydantic_commands/decorators.py
pydantic_commands/exceptions.py
pydantic_commands/executor.py
pydantic_commands/parser.py
pydantic_commands/py.typed
pydantic_commands/registry.py
pydantic_commands-0.1.0.dist-info/licenses/LICENSE
pydantic_commands-0.1.0.dist-info/METADATA
pydantic_commands-0.1.0.dist-info/WHEEL
pydantic_commands-0.1.0.dist-info/top_level.txt
pydantic_commands-0.1.0.dist-info/RECORD
