Metadata-Version: 2.4
Name: pydantic-commands
Version: 0.1.0
Summary: A Django-like command system with Pydantic model integration for automatic argparse generation
Author-email: Starscribers <Starscribers@gmail.com>
Project-URL: Homepage, https://github.com/Starscribers/python-packages
Project-URL: Repository, https://github.com/Starscribers/python-packages.git
Project-URL: Issues, https://github.com/Starscribers/python-packages/issues
Project-URL: Documentation, https://github.com/Starscribers/python-packages/blob/main/pydantic-commands/README.md
Classifier: Development Status :: 4 - Beta
Classifier: Intended Audience :: Developers
Classifier: License :: OSI Approved :: MIT License
Classifier: Operating System :: OS Independent
Classifier: Programming Language :: Python
Classifier: Programming Language :: Python :: 3
Classifier: Programming Language :: Python :: 3.9
Classifier: Programming Language :: Python :: 3.10
Classifier: Programming Language :: Python :: 3.11
Classifier: Programming Language :: Python :: 3.12
Classifier: Topic :: Software Development :: Libraries :: Python Modules
Classifier: Topic :: Utilities
Classifier: Typing :: Typed
Requires-Python: >=3.9
License-File: LICENSE
Requires-Dist: pydantic>=2.0.0
Requires-Dist: any-registries>=0.1.0
Provides-Extra: dev
Requires-Dist: pytest>=7.0.0; extra == "dev"
Requires-Dist: black>=22.0.0; extra == "dev"
Requires-Dist: isort>=5.10.0; extra == "dev"
Requires-Dist: mypy>=0.950; extra == "dev"
Requires-Dist: ruff>=0.13.1; extra == "dev"
Requires-Dist: pre-commit>=3.0.0; extra == "dev"
Requires-Dist: bandit>=1.7.0; extra == "dev"
Requires-Dist: twine>=4.0.0; extra == "dev"
Provides-Extra: testing
Requires-Dist: pytest>=7.0.0; extra == "testing"
Requires-Dist: pytest-cov>=3.0.0; extra == "testing"
Dynamic: license-file
